[
  {
    "url": "https://www.epcrugby.com/champions-cup/matches/282674/news",
    "home_team": "Bath Rugby",
    "away_team": "Stade Rochelais",
    "date": "Sat, 7 Dec 2024 - 05:00",
    "venue": "The Rec",
    "broadcasters": [
      "Premier Sports",
      "beIN SPORTS",
      "SuperSport",
      "FloRugby"
    ]
  },
  {
    "url": "https://www.epcrugby.com/champions-cup/matches/282675/news",
    "home_team": "ASM Clermont Auvergne",
    "away_team": "Benetton Rugby",
    "date": "Sat, 7 Dec 2024 - 22:00",
    "venue": "Stade Marcel-Michelin",
    "broadcasters": [
      "beIN SPORTS",
      "epcrugby.tv",
      "Premier Sports",
      "SuperSport",
      "FloRugby"
    ]
  },
  {
    "url": "https://www.epcrugby.com/champions-cup/matches/282676/news",
    "home_team": "Hollywoodbets Sharks",
    "away_team": "Exeter Chiefs",
    "date": "Sat, 7 Dec 2024 - 22:00",
    "venue": "Hollywoodbets Kings Park",
    "broadcasters": [
      "SuperSport",
      "Premier Sports",
      "beIN SPORTS",
      "FloRugby"
    ]
  },
  {
    "url": "https://www.epcrugby.com/champions-cup/matches/282677/news",
    "home_team": "Northampton Saints",
    "away_team": "Castres Olympique",
    "date": "Sun, 8 Dec 2024 - 00:15",
    "venue": "cinch Stadium @ Franklin's Gardens",
    "broadcasters": [
      "Premier Sports",
      "beIN SPORTS",
      "SuperSport",
      "FloRugby"
    ]
  },
  {
    "url": "https://www.epcrugby.com/champions-cup/matches/282678/news",
    "home_team": "DHL Stormers",
    "away_team": "RC Toulon",
    "date": "Sun, 8 Dec 2024 - 00:15",
    "venue": "Nelson Mandela Bay Stadium",
    "broadcasters": [
      "SuperSport",
      "beIN SPORTS",
      "France TV",
      "FloRugby",
      "Premier Sports"
    ]
  },
  {
    "url": "https://www.epcrugby.com/champions-cup/matches/282679/news",
    "home_team": "Munster Rugby",
    "away_team": "Stade Francais Paris",
    "date": "Sun, 8 Dec 2024 - 02:30",
    "venue": "Thomond Park",
    "broadcasters": [
      "RTE",
      "beIN SPORTS",
      "Premier Sports",
      "SuperSport",
      "FloRugby"
    ]
  },
  {
    "url": "https://www.epcrugby.com/champions-cup/matches/282680/news",
    "home_team": "Saracens",
    "away_team": "Vodacom Bulls",
    "date": "Sun, 8 Dec 2024 - 02:30",
    "venue": "StoneX Stadium",
    "broadcasters": [
      "Premier Sports",
      "SuperSport",
      "beIN SPORTS",
      "FloRugby"
    ]
  },
  {
    "url": "https://www.epcrugby.com/champions-cup/matches/282681/news",
    "home_team": "Glasgow Warriors",
    "away_team": "Sale Sharks",
    "date": "Sun, 8 Dec 2024 - 05:00",
    "venue": "Scotstoun Stadium",
    "broadcasters": [
      "Premier Sports",
      "beIN SPORTS",
      "SuperSport",
      "FloRugby"
    ]
  },
  {
    "url": "https://www.epcrugby.com/champions-cup/matches/282682/news",
    "home_team": "Racing 92",
    "away_team": "Harlequins",
    "date": "Sun, 8 Dec 2024 - 05:00",
    "venue": "Stade Dominique Duvauchelle",
    "broadcasters": [
      "beIN SPORTS",
      "Premier Sports",
      "SuperSport",
      "FloRugby"
    ]
  },
  {
    "url": "https://www.epcrugby.com/champions-cup/matches/282683/news",
    "home_team": "Union Bordeaux-Bègles",
    "away_team": "Leicester Tigers",
    "date": "Sun, 8 Dec 2024 - 22:00",
    "venue": "Stade Chaban-Delmas",
    "broadcasters": [
      "beIN SPORTS",
      "Premier Sports",
      "SuperSport",
      "FloRugby"
    ]
  },
  {
    "url": "https://www.epcrugby.com/champions-cup/matches/282684/news",
    "home_team": "Stade Toulousain",
    "away_team": "Ulster Rugby",
    "date": "Mon, 9 Dec 2024 - 00:15",
    "venue": "Stade Ernest Wallon",
    "broadcasters": [
      "Premier Sports",
      "France TV",
      "beIN SPORTS",
      "SuperSport",
      "FloRugby"
    ]
  },
  {
    "url": "https://www.epcrugby.com/champions-cup/matches/282685/news",
    "home_team": "Bristol Bears",
    "away_team": "Leinster Rugby",
    "date": "Mon, 9 Dec 2024 - 02:30",
    "venue": "Ashton Gate",
    "broadcasters": [
      "Premier Sports",
      "beIN SPORTS",
      "SuperSport",
      "FloRugby"
    ]
  },
  {
    "url": "https://www.epcrugby.com/champions-cup/matches/282686/news",
    "home_team": "Sale Sharks",
    "away_team": "Racing 92",
    "date": "Sat, 14 Dec 2024 - 05:00",
    "venue": "Salford Community Stadium",
    "broadcasters": [
      "Premier Sports",
      "beIN SPORTS",
      "FloRugby"
    ]
  },
  {
    "url": "https://www.epcrugby.com/champions-cup/matches/282687/news",
    "home_team": "Castres Olympique",
    "away_team": "Munster Rugby",
    "date": "Sat, 14 Dec 2024 - 05:00",
    "venue": "Stade Pierre-Fabre",
    "broadcasters": [
      "beIN SPORTS",
      "Premier Sports",
      "FloRugby"
    ]
  },
  {
    "url": "https://www.epcrugby.com/champions-cup/matches/282688/news",
    "home_team": "Vodacom Bulls",
    "away_team": "Northampton Saints",
    "date": "Sat, 14 Dec 2024 - 22:00",
    "venue": "Loftus Versfeld",
    "broadcasters": [
      "SuperSport",
      "Premier Sports",
      "beIN SPORTS",
      "FloRugby"
    ]
  },
  {
    "url": "https://www.epcrugby.com/champions-cup/matches/282689/news",
    "home_team": "Ulster Rugby",
    "away_team": "Union Bordeaux-Bègles",
    "date": "Sun, 15 Dec 2024 - 00:15",
    "venue": "Kingspan Stadium",
    "broadcasters": [
      "Premier Sports",
      "beIN SPORTS",
      "France TV",
      "FloRugby"
    ]
  },
  {
    "url": "https://www.epcrugby.com/champions-cup/matches/282690/news",
    "home_team": "Leinster Rugby",
    "away_team": "ASM Clermont Auvergne",
    "date": "Sun, 15 Dec 2024 - 02:30",
    "venue": "Aviva Stadium",
    "broadcasters": [
      "RTE",
      "beIN SPORTS",
      "Premier Sports",
      "FloRugby"
    ]
  },
  {
    "url": "https://www.epcrugby.com/champions-cup/matches/282691/news",
    "home_team": "Leicester Tigers",
    "away_team": "Hollywoodbets Sharks",
    "date": "Sun, 15 Dec 2024 - 02:30",
    "venue": "Mattioli Woods Welford Road",
    "broadcasters": [
      "Premier Sports",
      "SuperSport",
      "beIN SPORTS",
      "FloRugby"
    ]
  },
  {
    "url": "https://www.epcrugby.com/champions-cup/matches/282693/news",
    "home_team": "Stade Rochelais",
    "away_team": "Bristol Bears",
    "date": "Sun, 15 Dec 2024 - 05:00",
    "venue": "Stade Marcel Deflandre",
    "broadcasters": [
      "beIN SPORTS",
      "Premier Sports",
      "FloRugby"
    ]
  },
  {
    "url": "https://www.epcrugby.com/champions-cup/matches/282692/news",
    "home_team": "Harlequins",
    "away_team": "DHL Stormers",
    "date": "Sun, 15 Dec 2024 - 05:00",
    "venue": "Twickenham Stoop",
    "broadcasters": [
      "Premier Sports",
      "SuperSport",
      "beIN SPORTS",
      "FloRugby"
    ]
  },
  {
    "url": "https://www.epcrugby.com/champions-cup/matches/282695/news",
    "home_team": "Benetton Rugby",
    "away_team": "Bath Rugby",
    "date": "Sun, 15 Dec 2024 - 22:00",
    "venue": "Stadio Monigo",
    "broadcasters": [
      "Premier Sports",
      "epcrugby.tv",
      "beIN SPORTS",
      "FloRugby"
    ]
  },
  {
    "url": "https://www.epcrugby.com/champions-cup/matches/282696/news",
    "home_team": "Stade Francais Paris",
    "away_team": "Saracens",
    "date": "Sun, 15 Dec 2024 - 22:00",
    "venue": "Stade Jean Bouin",
    "broadcasters": [
      "Premier Sports",
      "beIN SPORTS",
      "FloRugby"
    ]
  },
  {
    "url": "https://www.epcrugby.com/champions-cup/matches/282694/news",
    "home_team": "RC Toulon",
    "away_team": "Glasgow Warriors",
    "date": "Mon, 16 Dec 2024 - 00:15",
    "venue": "Stade Felix Mayol",
    "broadcasters": [
      "beIN SPORTS",
      "Premier Sports",
      "France TV",
      "FloRugby"
    ]
  },
  {
    "url": "https://www.epcrugby.com/champions-cup/matches/282697/news",
    "home_team": "Exeter Chiefs",
    "away_team": "Stade Toulousain",
    "date": "Mon, 16 Dec 2024 - 02:30",
    "venue": "Sandy Park",
    "broadcasters": [
      "Premier Sports",
      "beIN SPORTS",
      "FloRugby"
    ]
  },
  {
    "url": "https://www.epcrugby.com/champions-cup/matches/282698/news",
    "home_team": "Glasgow Warriors",
    "away_team": "Racing 92",
    "date": "Sat, 11 Jan 2025 - 05:00",
    "venue": "Scotstoun Stadium",
    "broadcasters": [
      "Premier Sports",
      "beIN SPORTS",
      "SuperSport",
      "FloRugby"
    ]
  },
  {
    "url": "https://www.epcrugby.com/champions-cup/matches/282699/news",
    "home_team": "DHL Stormers",
    "away_team": "Sale Sharks",
    "date": "Sat, 11 Jan 2025 - 22:00",
    "venue": "DHL Stadium",
    "broadcasters": [
      "SuperSport",
      "Premier Sports",
      "beIN SPORTS",
      "FloRugby"
    ]
  },
  {
    "url": "https://www.epcrugby.com/champions-cup/matches/282700/news",
    "home_team": "Exeter Chiefs",
    "away_team": "Union Bordeaux-Bègles",
    "date": "Sun, 12 Jan 2025 - 00:15",
    "venue": "Sandy Park",
    "broadcasters": [
      "Premier Sports",
      "beIN SPORTS",
      "SuperSport",
      "FloRugby"
    ]
  },
  {
    "url": "https://www.epcrugby.com/champions-cup/matches/282701/news",
    "home_team": "Hollywoodbets Sharks",
    "away_team": "Stade Toulousain",
    "date": "Sun, 12 Jan 2025 - 00:15",
    "venue": "Hollywoodbets Kings Park",
    "broadcasters": [
      "SuperSport",
      "beIN SPORTS",
      "France TV",
      "Premier Sports",
      "FloRugby"
    ]
  },
  {
    "url": "https://www.epcrugby.com/champions-cup/matches/282702/news",
    "home_team": "Munster Rugby",
    "away_team": "Saracens",
    "date": "Sun, 12 Jan 2025 - 02:30",
    "venue": "Thomond Park",
    "broadcasters": [
      "RTE",
      "Premier Sports",
      "beIN SPORTS",
      "SuperSport",
      "FloRugby"
    ]
  },
  {
    "url": "https://www.epcrugby.com/champions-cup/matches/282703/news",
    "home_team": "Stade Francais Paris",
    "away_team": "Northampton Saints",
    "date": "Sun, 12 Jan 2025 - 02:30",
    "venue": "Stade Jean Bouin",
    "broadcasters": [
      "beIN SPORTS",
      "Premier Sports",
      "SuperSport",
      "FloRugby"
    ]
  },
  {
    "url": "https://www.epcrugby.com/champions-cup/matches/282704/news",
    "home_team": "Leicester Tigers",
    "away_team": "Ulster Rugby",
    "date": "Sun, 12 Jan 2025 - 05:00",
    "venue": "Mattioli Woods Welford Road",
    "broadcasters": [
      "Premier Sports",
      "beIN SPORTS",
      "SuperSport",
      "FloRugby"
    ]
  },
  {
    "url": "https://www.epcrugby.com/champions-cup/matches/282705/news",
    "home_team": "Castres Olympique",
    "away_team": "Vodacom Bulls",
    "date": "Sun, 12 Jan 2025 - 05:00",
    "venue": "Stade Pierre-Fabre",
    "broadcasters": [
      "beIN SPORTS",
      "SuperSport",
      "Premier Sports",
      "FloRugby"
    ]
  },
  {
    "url": "https://www.epcrugby.com/champions-cup/matches/282706/news",
    "home_team": "RC Toulon",
    "away_team": "Harlequins",
    "date": "Sun, 12 Jan 2025 - 22:00",
    "venue": "Stade Felix Mayol",
    "broadcasters": [
      "beIN SPORTS",
      "Premier Sports",
      "SuperSport",
      "FloRugby"
    ]
  },
  {
    "url": "https://www.epcrugby.com/champions-cup/matches/282707/news",
    "home_team": "Stade Rochelais",
    "away_team": "Leinster Rugby",
    "date": "Mon, 13 Jan 2025 - 00:15",
    "venue": "Stade Marcel Deflandre",
    "broadcasters": [
      "France TV",
      "Premier Sports",
      "beIN SPORTS",
      "SuperSport",
      "FloRugby"
    ]
  },
  {
    "url": "https://www.epcrugby.com/champions-cup/matches/282708/news",
    "home_team": "Bristol Bears",
    "away_team": "Benetton Rugby",
    "date": "Mon, 13 Jan 2025 - 00:15",
    "venue": "Ashton Gate",
    "broadcasters": [
      "Premier Sports",
      "epcrugby.tv",
      "beIN SPORTS",
      "SuperSport",
      "FloRugby"
    ]
  },
  {
    "url": "https://www.epcrugby.com/champions-cup/matches/282709/news",
    "home_team": "Bath Rugby",
    "away_team": "ASM Clermont Auvergne",
    "date": "Mon, 13 Jan 2025 - 02:30",
    "venue": "The Rec",
    "broadcasters": [
      "Premier Sports",
      "beIN SPORTS",
      "SuperSport",
      "FloRugby"
    ]
  },
  {
    "url": "https://www.epcrugby.com/champions-cup/matches/282710/news",
    "home_team": "Ulster Rugby",
    "away_team": "Exeter Chiefs",
    "date": "Sat, 18 Jan 2025 - 05:00",
    "venue": "Kingspan Stadium",
    "broadcasters": [
      "Premier Sports",
      "beIN SPORTS",
      "SuperSport",
      "FloRugby"
    ]
  },
  {
    "url": "https://www.epcrugby.com/champions-cup/matches/282711/news",
    "home_team": "Vodacom Bulls",
    "away_team": "Stade Francais Paris",
    "date": "Sat, 18 Jan 2025 - 22:00",
    "venue": "Loftus Versfeld",
    "broadcasters": [
      "SuperSport",
      "beIN SPORTS",
      "Premier Sports",
      "FloRugby"
    ]
  },
  {
    "url": "https://www.epcrugby.com/champions-cup/matches/282712/news",
    "home_team": "Northampton Saints",
    "away_team": "Munster Rugby",
    "date": "Sun, 19 Jan 2025 - 00:15",
    "venue": "cinch Stadium @ Franklin's Gardens",
    "broadcasters": [
      "Premier Sports",
      "beIN SPORTS",
      "SuperSport",
      "FloRugby"
    ]
  },
  {
    "url": "https://www.epcrugby.com/champions-cup/matches/282713/news",
    "home_team": "ASM Clermont Auvergne",
    "away_team": "Bristol Bears",
    "date": "Sun, 19 Jan 2025 - 00:15",
    "venue": "Stade Marcel-Michelin",
    "broadcasters": [
      "beIN SPORTS",
      "Premier Sports",
      "France TV",
      "SuperSport",
      "FloRugby"
    ]
  },
  {
    "url": "https://www.epcrugby.com/champions-cup/matches/282715/news",
    "home_team": "Benetton Rugby",
    "away_team": "Stade Rochelais",
    "date": "Sun, 19 Jan 2025 - 02:30",
    "venue": "Stadio Monigo",
    "broadcasters": [
      "epcrugby.tv",
      "beIN SPORTS",
      "Premier Sports",
      "SuperSport",
      "FloRugby"
    ]
  },
  {
    "url": "https://www.epcrugby.com/champions-cup/matches/282714/news",
    "home_team": "Leinster Rugby",
    "away_team": "Bath Rugby",
    "date": "Sun, 19 Jan 2025 - 02:30",
    "venue": "Aviva Stadium",
    "broadcasters": [
      "Premier Sports",
      "RTE",
      "beIN SPORTS",
      "SuperSport",
      "FloRugby"
    ]
  },
  {
    "url": "https://www.epcrugby.com/champions-cup/matches/282716/news",
    "home_team": "Harlequins",
    "away_team": "Glasgow Warriors",
    "date": "Sun, 19 Jan 2025 - 05:00",
    "venue": "Twickenham Stoop",
    "broadcasters": [
      "Premier Sports",
      "beIN SPORTS",
      "SuperSport",
      "FloRugby"
    ]
  },
  {
    "url": "https://www.epcrugby.com/champions-cup/matches/282717/news",
    "home_team": "Racing 92",
    "away_team": "DHL Stormers",
    "date": "Sun, 19 Jan 2025 - 05:00",
    "venue": "Paris La Defense Arena",
    "broadcasters": [
      "beIN SPORTS",
      "SuperSport",
      "Premier Sports",
      "FloRugby"
    ]
  },
  {
    "url": "https://www.epcrugby.com/champions-cup/matches/282718/news",
    "home_team": "Union Bordeaux-Bègles",
    "away_team": "Hollywoodbets Sharks",
    "date": "Sun, 19 Jan 2025 - 22:00",
    "venue": "Stade Chaban-Delmas",
    "broadcasters": [
      "beIN SPORTS",
      "SuperSport",
      "Premier Sports",
      "FloRugby"
    ]
  },
  {
    "url": "https://www.epcrugby.com/champions-cup/matches/282719/news",
    "home_team": "Saracens",
    "away_team": "Castres Olympique",
    "date": "Mon, 20 Jan 2025 - 00:15",
    "venue": "StoneX Stadium",
    "broadcasters": [
      "Premier Sports",
      "beIN SPORTS",
      "SuperSport",
      "FloRugby"
    ]
  },
  {
    "url": "https://www.epcrugby.com/champions-cup/matches/282720/news",
    "home_team": "Stade Toulousain",
    "away_team": "Leicester Tigers",
    "date": "Mon, 20 Jan 2025 - 00:15",
    "venue": "Stade Ernest Wallon",
    "broadcasters": [
      "France TV",
      "Premier Sports",
      "beIN SPORTS",
      "SuperSport",
      "FloRugby"
    ]
  },
  {
    "url": "https://www.epcrugby.com/champions-cup/matches/282721/news",
    "home_team": "Sale Sharks",
    "away_team": "RC Toulon",
    "date": "Mon, 20 Jan 2025 - 02:30",
    "venue": "Salford Community Stadium",
    "broadcasters": [
      "Premier Sports",
      "beIN SPORTS",
      "SuperSport",
      "FloRugby"
    ]
  },
  {
    "url": "https://www.epcrugby.com/champions-cup/matches/282724/news",
    "home_team": "Northampton Saints",
    "away_team": "ASM Clermont Auvergne",
    "date": "Sat, 5 Apr 2025 - 04:00",
    "venue": "cinch Stadium @ Franklin's Gardens",
    "broadcasters": [
      "Premier Sports",
      "beIN SPORTS",
      "SuperSport",
      "FloRugby"
    ]
  },
  {
    "url": "https://www.epcrugby.com/champions-cup/matches/282725/news",
    "home_team": "RC Toulon",
    "away_team": "Saracens",
    "date": "Sat, 5 Apr 2025 - 20:30",
    "venue": "Stade Felix Mayol",
    "broadcasters": [
      "beIN SPORTS",
      "Premier Sports",
      "SuperSport",
      "FloRugby"
    ]
  },
  {
    "url": "https://www.epcrugby.com/champions-cup/matches/282723/news",
    "home_team": "Leinster Rugby",
    "away_team": "Harlequins",
    "date": "Sat, 5 Apr 2025 - 23:00",
    "venue": "Croke Park",
    "broadcasters": [
      "RTE",
      "Premier Sports",
      "beIN SPORTS",
      "SuperSport",
      "FloRugby"
    ]
  },
  {
    "url": "https://www.epcrugby.com/champions-cup/matches/282727/news",
    "home_team": "Castres Olympique",
    "away_team": "Benetton Rugby",
    "date": "Sat, 5 Apr 2025 - 23:00",
    "venue": "Stade Pierre-Fabre",
    "broadcasters": [
      "beIN SPORTS",
      "France TV",
      "epcrugby.tv",
      "Premier Sports",
      "SuperSport",
      "FloRugby"
    ]
  },
  {
    "url": "https://www.epcrugby.com/champions-cup/matches/282729/news",
    "home_team": "Stade Rochelais",
    "away_team": "Munster Rugby",
    "date": "Sun, 6 Apr 2025 - 01:30",
    "venue": "Stade Marcel Deflandre",
    "broadcasters": [
      "beIN SPORTS",
      "Premier Sports",
      "SuperSport",
      "FloRugby"
    ]
  },
  {
    "url": "https://www.epcrugby.com/champions-cup/matches/282728/news",
    "home_team": "Glasgow Warriors",
    "away_team": "Leicester Tigers",
    "date": "Sun, 6 Apr 2025 - 04:00",
    "venue": "Scotstoun Stadium",
    "broadcasters": [
      "Premier Sports",
      "beIN SPORTS",
      "SuperSport",
      "FloRugby"
    ]
  },
  {
    "url": "https://www.epcrugby.com/champions-cup/matches/282722/news",
    "home_team": "Union Bordeaux-Bègles",
    "away_team": "Ulster Rugby",
    "date": "Sun, 6 Apr 2025 - 20:30",
    "venue": "Stade Chaban-Delmas",
    "broadcasters": [
      "Premier Sports",
      "beIN SPORTS",
      "SuperSport",
      "FloRugby"
    ]
  },
  {
    "url": "https://www.epcrugby.com/champions-cup/matches/282726/news",
    "home_team": "Stade Toulousain",
    "away_team": "Sale Sharks",
    "date": "Sun, 6 Apr 2025 - 23:00",
    "venue": "Stadium de Toulouse",
    "broadcasters": [
      "France TV",
      "beIN SPORTS",
      "Premier Sports",
      "SuperSport",
      "FloRugby"
    ]
  },
  {
    "home_team": "",
    "away_team": "",
    "date": "TBC",
    "venue": "TBD"
  },
  {
    "home_team": "",
    "away_team": "",
    "date": "TBC",
    "venue": "TBD"
  },
  {
    "home_team": "",
    "away_team": "",
    "date": "TBC",
    "venue": "TBD"
  },
  {
    "home_team": "",
    "away_team": "",
    "date": "TBC",
    "venue": "TBD"
  },
  {
    "home_team": "",
    "away_team": "",
    "date": "TBC",
    "venue": "TBD"
  },
  {
    "home_team": "",
    "away_team": "",
    "date": "TBC",
    "venue": "TBD"
  },
  {
    "home_team": "",
    "away_team": "",
    "date": "TBC",
    "venue": "Principality Stadium"
  }
]