{
  "m6n-1": {
    "id": "m6n-1",
    "competition_id": "m6n",
    "name": "England",
    "name_ja": "イングランド",
    "short_name": "ENG",
    "country": "England",
    "division": "",
    "logo_url": "",
    "badge_url": ""
  },
  "m6n-2": {
    "id": "m6n-2",
    "competition_id": "m6n",
    "name": "France",
    "name_ja": "フランス",
    "short_name": "FRA",
    "country": "France",
    "division": "",
    "logo_url": "",
    "badge_url": ""
  },
  "m6n-3": {
    "id": "m6n-3",
    "competition_id": "m6n",
    "name": "Ireland",
    "name_ja": "アイルランド",
    "short_name": "IRE",
    "country": "Ireland",
    "division": "",
    "logo_url": "",
    "badge_url": ""
  },
  "m6n-4": {
    "id": "m6n-4",
    "competition_id": "m6n",
    "name": "Italy",
    "name_ja": "イタリア",
    "short_name": "ITA",
    "country": "Italy",
    "division": "",
    "logo_url": "",
    "badge_url": ""
  },
  "m6n-5": {
    "id": "m6n-5",
    "competition_id": "m6n",
    "name": "Scotland",
    "name_ja": "スコットランド",
    "short_name": "SCO",
    "country": "Scotland",
    "division": "",
    "logo_url": "",
    "badge_url": ""
  },
  "m6n-6": {
    "id": "m6n-6",
    "competition_id": "m6n",
    "name": "Wales",
    "name_ja": "ウェールズ",
    "short_name": "WAL",
    "country": "Wales",
    "division": "",
    "logo_url": "",
    "badge_url": ""
  },
  "w6n-1": {
    "id": "w6n-1",
    "competition_id": "w6n",
    "name": "England",
    "name_ja": "イングランド",
    "short_name": "ENG",
    "country": "England",
    "division": "",
    "logo_url": "",
    "badge_url": ""
  },
  "w6n-2": {
    "id": "w6n-2",
    "competition_id": "w6n",
    "name": "France",
    "name_ja": "フランス",
    "short_name": "FRA",
    "country": "France",
    "division": "",
    "logo_url": "",
    "badge_url": ""
  },
  "w6n-3": {
    "id": "w6n-3",
    "competition_id": "w6n",
    "name": "Ireland",
    "name_ja": "アイルランド",
    "short_name": "IRE",
    "country": "Ireland",
    "division": "",
    "logo_url": "",
    "badge_url": ""
  },
  "w6n-4": {
    "id": "w6n-4",
    "competition_id": "w6n",
    "name": "Italy",
    "name_ja": "イタリア",
    "short_name": "ITA",
    "country": "Italy",
    "division": "",
    "logo_url": "",
    "badge_url": ""
  },
  "w6n-5": {
    "id": "w6n-5",
    "competition_id": "w6n",
    "name": "Scotland",
    "name_ja": "スコットランド",
    "short_name": "SCO",
    "country": "Scotland",
    "division": "",
    "logo_url": "",
    "badge_url": ""
  },
  "w6n-6": {
    "id": "w6n-6",
    "competition_id": "w6n",
    "name": "Wales",
    "name_ja": "ウェールズ",
    "short_name": "WAL",
    "country": "Wales",
    "division": "",
    "logo_url": "",
    "badge_url": ""
  },
  "u6n-1": {
    "id": "u6n-1",
    "competition_id": "u6n",
    "name": "England",
    "name_ja": "イングランド",
    "short_name": "ENG",
    "country": "England",
    "division": "",
    "logo_url": "",
    "badge_url": ""
  },
  "u6n-2": {
    "id": "u6n-2",
    "competition_id": "u6n",
    "name": "France",
    "name_ja": "フランス",
    "short_name": "FRA",
    "country": "France",
    "division": "",
    "logo_url": "",
    "badge_url": ""
  },
  "u6n-3": {
    "id": "u6n-3",
    "competition_id": "u6n",
    "name": "Ireland",
    "name_ja": "アイルランド",
    "short_name": "IRE",
    "country": "Ireland",
    "division": "",
    "logo_url": "",
    "badge_url": ""
  },
  "u6n-4": {
    "id": "u6n-4",
    "competition_id": "u6n",
    "name": "Italy",
    "name_ja": "イタリア",
    "short_name": "ITA",
    "country": "Italy",
    "division": "",
    "logo_url": "",
    "badge_url": ""
  },
  "u6n-5": {
    "id": "u6n-5",
    "competition_id": "u6n",
    "name": "Scotland",
    "name_ja": "スコットランド",
    "short_name": "SCO",
    "country": "Scotland",
    "division": "",
    "logo_url": "",
    "badge_url": ""
  },
  "u6n-6": {
    "id": "u6n-6",
    "competition_id": "u6n",
    "name": "Wales",
    "name_ja": "ウェールズ",
    "short_name": "WAL",
    "country": "Wales",
    "division": "",
    "logo_url": "",
    "badge_url": ""
  },
  "jrlo-1": {
    "id": "jrlo-1",
    "competition_id": "jrlo",
    "name": "Saitama Wild Knights",
    "name_ja": "埼玉ワイルドナイツ",
    "short_name": "Wild Knights",
    "country": "",
    "division": "Division 1",
    "logo_url": "",
    "badge_url": ""
  },
  "jrlo-2": {
    "id": "jrlo-2",
    "competition_id": "jrlo",
    "name": "Tokyo Sungoliath",
    "name_ja": "東京サンゴリアス",
    "short_name": "Sungoliath",
    "country": "",
    "division": "Division 1",
    "logo_url": "",
    "badge_url": ""
  },
  "jrlo-3": {
    "id": "jrlo-3",
    "competition_id": "jrlo",
    "name": "Kubota Spears",
    "name_ja": "クボタスピアーズ船橋・東京ベイ",
    "short_name": "Spears",
    "country": "",
    "division": "Division 1",
    "logo_url": "",
    "badge_url": ""
  },
  "jrlo-4": {
    "id": "jrlo-4",
    "competition_id": "jrlo",
    "name": "Toyota Verblitz",
    "name_ja": "トヨタヴェルブリッツ",
    "short_name": "Verblitz",
    "country": "",
    "division": "Division 1",
    "logo_url": "",
    "badge_url": ""
  },
  "jrlo-5": {
    "id": "jrlo-5",
    "competition_id": "jrlo",
    "name": "Toshiba Brave Lupus Tokyo",
    "name_ja": "東芝ブレイブルーパス東京",
    "short_name": "Brave Lupus",
    "country": "",
    "division": "Division 1",
    "logo_url": "",
    "badge_url": ""
  },
  "jrlo-6": {
    "id": "jrlo-6",
    "competition_id": "jrlo",
    "name": "Yokohama Canon Eagles",
    "name_ja": "横浜キヤノンイーグルス",
    "short_name": "Eagles",
    "country": "",
    "division": "Division 1",
    "logo_url": "",
    "badge_url": ""
  },
  "jrlo-7": {
    "id": "jrlo-7",
    "competition_id": "jrlo",
    "name": "Kobelco Kobe Steelers",
    "name_ja": "コベルコ神戸スティーラーズ",
    "short_name": "Steelers",
    "country": "",
    "division": "Division 1",
    "logo_url": "",
    "badge_url": ""
  },
  "jrlo-8": {
    "id": "jrlo-8",
    "competition_id": "jrlo",
    "name": "Black Rams Tokyo",
    "name_ja": "ブラックラムズ東京",
    "short_name": "Black Rams",
    "country": "",
    "division": "Division 1",
    "logo_url": "",
    "badge_url": ""
  },
  "jrlo-9": {
    "id": "jrlo-9",
    "competition_id": "jrlo",
    "name": "Ricoh Black Rams Tokyo",
    "name_ja": "リコーブラックラムズ東京",
    "short_name": "Ricoh Black Rams",
    "country": "",
    "division": "Division 1",
    "logo_url": "",
    "badge_url": ""
  },
  "jrlo-10": {
    "id": "jrlo-10",
    "competition_id": "jrlo",
    "name": "Shizuoka Blue Revs",
    "name_ja": "静岡ブルーレヴズ",
    "short_name": "Blue Revs",
    "country": "",
    "division": "Division 1",
    "logo_url": "",
    "badge_url": ""
  },
  "jrlo-11": {
    "id": "jrlo-11",
    "competition_id": "jrlo",
    "name": "Mie Honda Heat",
    "name_ja": "三重ホンダヒート",
    "short_name": "Mie Honda",
    "country": "",
    "division": "Division 1",
    "logo_url": "",
    "badge_url": ""
  },
  "jrlo-12": {
    "id": "jrlo-12",
    "competition_id": "jrlo",
    "name": "Hanazono Kintetsu Liners",
    "name_ja": "花園近鉄ライナーズ",
    "short_name": "Liners",
    "country": "",
    "division": "Division 1",
    "logo_url": "",
    "badge_url": ""
  },
  "trc-1": {
    "id": "trc-1",
    "competition_id": "trc",
    "name": "Argentina",
    "name_ja": "アルゼンチン",
    "short_name": "ARG",
    "country": "Argentina",
    "division": "",
    "logo_url": "",
    "badge_url": ""
  },
  "trc-2": {
    "id": "trc-2",
    "competition_id": "trc",
    "name": "Australia",
    "name_ja": "オーストラリア",
    "short_name": "AUS",
    "country": "Australia",
    "division": "",
    "logo_url": "",
    "badge_url": ""
  },
  "trc-3": {
    "id": "trc-3",
    "competition_id": "trc",
    "name": "New Zealand",
    "name_ja": "ニュージーランド",
    "short_name": "NZL",
    "country": "New Zealand",
    "division": "",
    "logo_url": "",
    "badge_url": ""
  },
  "trc-4": {
    "id": "trc-4",
    "competition_id": "trc",
    "name": "South Africa",
    "name_ja": "南アフリカ",
    "short_name": "RSA",
    "country": "South Africa",
    "division": "",
    "logo_url": "",
    "badge_url": ""
  }
}
